{"cameraMode":{"drawMode":0,"name":"Shaded","section":"Shading Mode"},"sceneLighting":true,"audioPlay":false,"sceneViewState":{"m_AlwaysRefresh":false,"showFog":true,"showSkybox":true,"showFlares":true,"showImageEffects":true,"showParticleSystems":true,"showVisualEffectGraphs":true,"m_FxEnabled":true},"in2DMode":false,"pivot":{"x":12.817330360412598,"y":3.1367969512939455,"z":15.830156326293946},"rotation":{"x":-0.28035277128219607,"y":-0.5404255390167236,"z":0.1971403807401657,"w":-0.7684552669525147},"size":0.4876333475112915,"orthographic":false}